auglichem/__init__.py
auglichem/crystal/__init__.py
auglichem/crystal/_transforms.py
auglichem/crystal/data/__init__.py
auglichem/crystal/data/_crystal_dataset.py
auglichem/crystal/data/_knn.py
auglichem/crystal/data/_load_sets.py
auglichem/crystal/models/__init__.py
auglichem/crystal/models/_radius_graph.py
auglichem/crystal/models/cgcnn.py
auglichem/crystal/models/gcn.py
auglichem/crystal/models/gin.py
auglichem/crystal/models/schnet.py
auglichem/molecule/__init__.py
auglichem/molecule/_compositions.py
auglichem/molecule/_transforms.py
auglichem/molecule/data/__init__.py
auglichem/molecule/data/_load_sets.py
auglichem/molecule/data/_molecule_dataset.py
auglichem/molecule/models/__init__.py
auglichem/molecule/models/afp.py
auglichem/molecule/models/deepgcn.py
auglichem/molecule/models/gcn.py
auglichem/molecule/models/gine.py
auglichem/utils/__init__.py
auglichem/utils/_constants.py
auglichem/utils/_splitting.py
auglichem-0.1.8.dist-info/LICENSE
auglichem-0.1.8.dist-info/METADATA
auglichem-0.1.8.dist-info/WHEEL
auglichem-0.1.8.dist-info/top_level.txt
auglichem-0.1.8.dist-info/RECORD
