Metadata-Version: 2.1
Name: auglichem
Version: 0.1.8
Summary: Data augmentation of molecules and crystals.
Home-page: https://github.com/BaratiLab/AugLiChem
Author: Yuyang Wange, Rishikesh Magar, Cooper Lorsung, Hariharan Ramasubramanian, Chen Liang, Peiyuan Li, Amir Barati Farimani
Author-email: clorsung@andrew.cmu.edu
License: MIT
Classifier: Intended Audience :: Developers
Classifier: License :: OSI Approved :: MIT License
Classifier: Programming Language :: Python :: 3
Classifier: Operating System :: OS Independent
Requires-Python: >=3.8
License-File: LICENSE
Requires-Dist: numpy (>=1.21.1)
Requires-Dist: pytest (>=6.0.1)
Requires-Dist: pytest-cov
Requires-Dist: sklearn
Requires-Dist: pandas (>=1.3.1)
Requires-Dist: matplotlib (>=3.4.2)
Requires-Dist: pyyaml (>=5.4.1)
Requires-Dist: tqdm
Requires-Dist: ase (>=3.22.0)
Requires-Dist: pymatgen (>=2022.0.11)
Requires-Dist: rdflib
Requires-Dist: torch (>=1.10)
Requires-Dist: rdkit-pypi
Requires-Dist: tensorboard (>=2.4.1)
